setup.py
bcbio/__init__.py
bcbio/phylo/__init__.py
bcbio/phylo/blast.py
bcbio_phyloblast.egg-info/PKG-INFO
bcbio_phyloblast.egg-info/SOURCES.txt
bcbio_phyloblast.egg-info/dependency_links.txt
bcbio_phyloblast.egg-info/namespace_packages.txt
bcbio_phyloblast.egg-info/top_level.txt
scripts/blast_cross_orgs.py
scripts/retrieve_org_dbs.py