Metadata-Version: 1.0
Name: bcbio-phyloblast
Version: 0.1.2
Summary: Distributed BLAST for gene phylogeny estimation
Home-page: http://bcbio.wordpress.com
Author: Brad Chapman
Author-email: chapmanb@50mail.com
License: MIT
Platform: UNKNOWN
